datamerger/__init__.py
datamerger/datamerger.py
datamerger-0.1.10.dist-info/WHEEL
datamerger-0.1.10.dist-info/METADATA
datamerger-0.1.10.dist-info/RECORD
