Metadata-Version: 2.1
Name: datamerger
Version: 0.1.10
Summary: Quick tools to easily merge multiple, multi-dimensional datasets based on arbitrary attributes and criteria.
License: MIT
Author: Max Fan
Author-email: theinnovativeinventor@gmail.com
Requires-Python: >=3.8,<4.0
Classifier: License :: OSI Approved :: MIT License
Classifier: Programming Language :: Python :: 3
Classifier: Programming Language :: Python :: 3.8
Requires-Dist: pandas (>=1.2.0,<2.0.0)
Requires-Dist: tqdm (>=4.55.1,<5.0.0)
